MANIFEST.in
setup.py
humilis_sam/__init__.py
humilis_sam/meta.yaml.j2
humilis_sam/outputs.yaml.j2
humilis_sam/plugin.py
humilis_sam/resources.yaml.j2
humilis_sam/swagger.yaml.j2
humilis_sam/transform.yaml.j2
humilis_sam.egg-info/PKG-INFO
humilis_sam.egg-info/SOURCES.txt
humilis_sam.egg-info/dependency_links.txt
humilis_sam.egg-info/entry_points.txt
humilis_sam.egg-info/not-zip-safe
humilis_sam.egg-info/requires.txt
humilis_sam.egg-info/top_level.txt
humilis_sam/lambda_function/__init__.py
humilis_sam/lambda_function/setup.py
humilis_sam/lambda_function/handler/__init__.py