Metadata-Version: 1.1
Name: humilis-sam
Version: 0.0.8
Summary: Humilis plug-in to deploy a SAM application
Home-page: https://github.com/humilis/humilis-sam
Author: Arnaud Charpentier, FindHotel BV
Author-email: arnaud@findhotel.net
License: MIT
Platform: UNKNOWN
Classifier: Programming Language :: Python :: 3
Classifier: Programming Language :: Python :: 2
